{"@context":"https://iiif.io/api/presentation/3/context.json","id":"https://elliotdwilliams.github.io/tcdl-canopy-workshop/api/facet/date-original/1991-1997-and-undated.json","type":"Collection","label":{"none":["1991-1997 and undated"]},"items":[{"id":"https://cdm16018.contentdm.oclc.org/iiif/p16018coll5:445/manifest.json","type":"Manifest","label":{"none":["Living Wage reports and articles"]},"thumbnail":[{"id":"https://cdm16018.contentdm.oclc.org/iiif/2/p16018coll5:388/full/395,/0/default.jpg","type":"Image","format":"image/jpeg","width":395,"height":127}],"homepage":[{"id":"https://elliotdwilliams.github.io/tcdl-canopy-workshop/works/living-wage-reports-and-articles","type":"Text","label":{"none":["Living Wage reports and articles"]}}]}],"partOf":[{"id":"https://elliotdwilliams.github.io/tcdl-canopy-workshop/api/facet/date-original.json","type":"Collection"}],"summary":{"none":["Date-Original"]},"homepage":[{"id":"https://elliotdwilliams.github.io/tcdl-canopy-workshop/search?date-original=1991-1997-and-undated","type":"Text","label":{"none":["1991-1997 and undated"]}}]}